onlinejudge/__about__.py
onlinejudge/__init__.py
onlinejudge/dispatch.py
onlinejudge/py.typed
onlinejudge/type.py
onlinejudge/utils.py
onlinejudge/_implementation/__init__.py
onlinejudge/_implementation/format_utils.py
onlinejudge/_implementation/language_guessing.py
onlinejudge/_implementation/testcase_zipper.py
onlinejudge/_implementation/utils.py
onlinejudge/service/__init__.py
onlinejudge/service/anarchygolf.py
onlinejudge/service/aoj.py
onlinejudge/service/atcoder.py
onlinejudge/service/atcoder_problems.py
onlinejudge/service/codechef.py
onlinejudge/service/codeforces.py
onlinejudge/service/csacademy.py
onlinejudge/service/facebook.py
onlinejudge/service/google.py
onlinejudge/service/hackerrank.py
onlinejudge/service/kagamiz.py
onlinejudge/service/kattis.py
onlinejudge/service/library_checker.py
onlinejudge/service/poj.py
onlinejudge/service/spoj.py
onlinejudge/service/topcoder.py
onlinejudge/service/toph.py
onlinejudge/service/yukicoder.py
onlinejudge_api/__init__.py
onlinejudge_api/get_contest.py
onlinejudge_api/get_problem.py
onlinejudge_api/get_service.py
onlinejudge_api/guess_language_id.py
onlinejudge_api/login_service.py
onlinejudge_api/main.py
onlinejudge_api/submit_code.py
onlinejudge_workaround_for_conflict/__about__.py
onlinejudge_workaround_for_conflict/__init__.py
onlinejudge_workaround_for_conflict/dispatch.py
onlinejudge_workaround_for_conflict/py.typed
onlinejudge_workaround_for_conflict/type.py
onlinejudge_workaround_for_conflict/utils.py
onlinejudge_workaround_for_conflict/_implementation/__init__.py
onlinejudge_workaround_for_conflict/_implementation/format_utils.py
onlinejudge_workaround_for_conflict/_implementation/language_guessing.py
onlinejudge_workaround_for_conflict/_implementation/testcase_zipper.py
onlinejudge_workaround_for_conflict/_implementation/utils.py
onlinejudge_workaround_for_conflict/service/__init__.py
onlinejudge_workaround_for_conflict/service/anarchygolf.py
onlinejudge_workaround_for_conflict/service/aoj.py
online_judge_api_client-10.10.0.dist-info/LICENSE
online_judge_api_client-10.10.0.dist-info/METADATA
online_judge_api_client-10.10.0.dist-info/WHEEL
online_judge_api_client-10.10.0.dist-info/entry_points.txt
online_judge_api_client-10.10.0.dist-info/top_level.txt
online_judge_api_client-10.10.0.dist-info/RECORD
