Metadata-Version: 2.1
Name: online-judge-api-client
Version: 10.10.0
Summary: API client to develop tools for competitive programming
Home-page: https://github.com/online-judge-tools/api-client
Author: Kimiyuki Onaka
Author-email: kimiyuki95@gmail.com
License: MIT License
Platform: UNKNOWN
Classifier: Development Status :: 5 - Production/Stable
Classifier: Environment :: Console
Classifier: Intended Audience :: Developers
Classifier: License :: OSI Approved :: MIT License
Classifier: Operating System :: OS Independent
Classifier: Programming Language :: Python :: 3.5
Classifier: Programming Language :: Python :: 3.6
Classifier: Topic :: Internet :: WWW/HTTP
Classifier: Topic :: Software Development
Classifier: Topic :: Text Processing :: Markup :: HTML
Classifier: Topic :: Utilities
Requires-Python: >=3.6
Requires-Dist: appdirs (>=1)
Requires-Dist: beautifulsoup4 (>=4)
Requires-Dist: colorlog (>=4.1.0)
Requires-Dist: lxml (>=4)
Requires-Dist: requests (>=2)
Requires-Dist: toml (>=0.10)
Requires-Dist: jsonschema (>=3.2)
Provides-Extra: dev
Requires-Dist: isort (==5.7.0) ; extra == 'dev'
Requires-Dist: mypy (==0.812) ; extra == 'dev'
Requires-Dist: pylint (==2.7.2) ; extra == 'dev'
Requires-Dist: yapf (==0.30.0) ; extra == 'dev'
Requires-Dist: pytest (>=5.1.2) ; extra == 'dev'
Requires-Dist: pytest-cov (>=2.7.1) ; extra == 'dev'
Provides-Extra: docs
Requires-Dist: sphinx (>=2.4) ; extra == 'docs'
Requires-Dist: sphinx-rtd-theme (>=0.4) ; extra == 'docs'
